fe/__init__.py
frog_encryption-0.0.1.dist-info/LICENSE
frog_encryption-0.0.1.dist-info/METADATA
frog_encryption-0.0.1.dist-info/WHEEL
frog_encryption-0.0.1.dist-info/top_level.txt
frog_encryption-0.0.1.dist-info/RECORD
